odoo/addons/account_move_multi_company/README.rst
odoo/addons/account_move_multi_company/__init__.py
odoo/addons/account_move_multi_company/__manifest__.py
odoo/addons/account_move_multi_company/i18n/account_move_multi_company.pot
odoo/addons/account_move_multi_company/models/__init__.py
odoo/addons/account_move_multi_company/models/account_move.py
odoo/addons/account_move_multi_company/models/account_move_line.py
odoo/addons/account_move_multi_company/readme/CONFIGURE.rst
odoo/addons/account_move_multi_company/readme/CONTRIBUTORS.rst
odoo/addons/account_move_multi_company/readme/CREDITS.rst
odoo/addons/account_move_multi_company/readme/DESCRIPTION.rst
odoo/addons/account_move_multi_company/readme/USAGE.rst
odoo/addons/account_move_multi_company/security/ir_rule.xml
odoo/addons/account_move_multi_company/static/description/icon.png
odoo/addons/account_move_multi_company/static/description/index.html
odoo/addons/account_move_multi_company/tests/__init__.py
odoo/addons/account_move_multi_company/tests/test_account_move.py
odoo/addons/account_move_multi_company/views/account_move_view.xml
odoo12_addon_account_move_multi_company-12.0.1.0.3.dist-info/METADATA
odoo12_addon_account_move_multi_company-12.0.1.0.3.dist-info/WHEEL
odoo12_addon_account_move_multi_company-12.0.1.0.3.dist-info/top_level.txt
odoo12_addon_account_move_multi_company-12.0.1.0.3.dist-info/RECORD
